[
    {
        "Team": "MEM",
        "Match Up": "MEM @ LAL",
        "Date": "04/28/2023",
        "Result": "L",
        "Minutes": "26",
        "Points": "10",
        "FGM": "4",
        "FGA": "11",
        "FG%": "36.4",
        "3PM": "2",
        "3PA": "5",
        "3P%": "40.0",
        "FTM": "0",
        "FTA": "0",
        "FT%": "-",
        "OREB": "1",
        "DREB": "3",
        "REB": "4",
        "AST": "2",
        "STL": "0",
        "BLK": "0",
        "TOV": "1",
        "PF": "1",
        "+/-": "-23",
        "FP": "16.8"
    },
    {
        "Team": "MEM",
        "Match Up": "MEM vs. LAL",
        "Date": "04/26/2023",
        "Result": "W",
        "Minutes": "30",
        "Points": "8",
        "FGM": "3",
        "FGA": "15",
        "FG%": "20.0",
        "3PM": "2",
        "3PA": "10",
        "3P%": "20.0",
        "FTM": "0",
        "FTA": "0",
        "FT%": "-",
        "OREB": "0",
        "DREB": "2",
        "REB": "2",
        "AST": "0",
        "STL": "0",
        "BLK": "0",
        "TOV": "1",
        "PF": "4",
        "+/-": "-7",
        "FP": "9.4"
    },
    {
        "Team": "MEM",
        "Match Up": "MEM @ LAL",
        "Date": "04/24/2023",
        "Result": "L",
        "Minutes": "41",
        "Points": "11",
        "FGM": "4",
        "FGA": "11",
        "FG%": "36.4",
        "3PM": "1",
        "3PA": "7",
        "3P%": "14.3",
        "FTM": "2",
        "FTA": "2",
        "FT%": "100",
        "OREB": "1",
        "DREB": "4",
        "REB": "5",
        "AST": "4",
        "STL": "0",
        "BLK": "0",
        "TOV": "1",
        "PF": "5",
        "+/-": "2",
        "FP": "22.0"
    },
    {
        "Team": "MEM",
        "Match Up": "MEM @ LAL",
        "Date": "04/22/2023",
        "Result": "L",
        "Minutes": "19",
        "Points": "7",
        "FGM": "3",
        "FGA": "13",
        "FG%": "23.1",
        "3PM": "1",
        "3PA": "5",
        "3P%": "20.0",
        "FTM": "0",
        "FTA": "1",
        "FT%": "0.0",
        "OREB": "1",
        "DREB": "1",
        "REB": "2",
        "AST": "0",
        "STL": "1",
        "BLK": "0",
        "TOV": "1",
        "PF": "2",
        "+/-": "-6",
        "FP": "11.4"
    },
    {
        "Team": "MEM",
        "Match Up": "MEM vs. LAL",
        "Date": "04/19/2023",
        "Result": "W",
        "Minutes": "23",
        "Points": "12",
        "FGM": "5",
        "FGA": "14",
        "FG%": "35.7",
        "3PM": "2",
        "3PA": "6",
        "3P%": "33.3",
        "FTM": "0",
        "FTA": "0",
        "FT%": "-",
        "OREB": "0",
        "DREB": "1",
        "REB": "1",
        "AST": "3",
        "STL": "0",
        "BLK": "0",
        "TOV": "2",
        "PF": "5",
        "+/-": "8",
        "FP": "15.7"
    },
    {
        "Team": "MEM",
        "Match Up": "MEM vs. LAL",
        "Date": "04/16/2023",
        "Result": "L",
        "Minutes": "29",
        "Points": "15",
        "FGM": "5",
        "FGA": "13",
        "FG%": "38.5",
        "3PM": "2",
        "3PA": "9",
        "3P%": "22.2",
        "FTM": "3",
        "FTA": "4",
        "FT%": "75.0",
        "OREB": "0",
        "DREB": "4",
        "REB": "4",
        "AST": "2",
        "STL": "0",
        "BLK": "0",
        "TOV": "1",
        "PF": "3",
        "+/-": "-18",
        "FP": "21.8"
    }
]