[
    {
        "Team": "CLE",
        "Match Up": "CLE @ NYK",
        "Date": "04/21/2023",
        "Result": "L",
        "Minutes": "4",
        "Points": "0",
        "FGM": "0",
        "FGA": "0",
        "FG%": "-",
        "3PM": "0",
        "3PA": "0",
        "3P%": "-",
        "FTM": "0",
        "FTA": "0",
        "FT%": "-",
        "OREB": "0",
        "DREB": "2",
        "REB": "2",
        "AST": "0",
        "STL": "0",
        "BLK": "0",
        "TOV": "0",
        "PF": "0",
        "+/-": "6",
        "FP": "2.4"
    },
    {
        "Team": "CLE",
        "Match Up": "CLE vs. NYK",
        "Date": "04/15/2023",
        "Result": "L",
        "Minutes": "7",
        "Points": "2",
        "FGM": "0",
        "FGA": "1",
        "FG%": "0.0",
        "3PM": "0",
        "3PA": "1",
        "3P%": "0.0",
        "FTM": "2",
        "FTA": "2",
        "FT%": "100",
        "OREB": "0",
        "DREB": "1",
        "REB": "1",
        "AST": "0",
        "STL": "0",
        "BLK": "0",
        "TOV": "0",
        "PF": "0",
        "+/-": "-14",
        "FP": "3.2"
    }
]