[
    {
        "Team": "UTA",
        "Match Up": "UTA @ LAL",
        "Date": "04/14/2009",
        "Result": "L",
        "Minutes": "36",
        "Points": "16",
        "FGM": "5",
        "FGA": "11",
        "FG%": "45.5",
        "3PM": "0",
        "3PA": "0",
        "3P%": "-",
        "FTM": "6",
        "FTA": "9",
        "FT%": "66.7",
        "OREB": "3",
        "DREB": "6",
        "REB": "9",
        "AST": "1",
        "STL": "0",
        "BLK": "1",
        "TOV": "2",
        "PF": "5",
        "+/-": "-10",
        "FP": "29.3"
    },
    {
        "Team": "UTA",
        "Match Up": "UTA vs. LAC",
        "Date": "04/13/2009",
        "Result": "W",
        "Minutes": "32",
        "Points": "20",
        "FGM": "8",
        "FGA": "15",
        "FG%": "53.3",
        "3PM": "0",
        "3PA": "0",
        "3P%": "-",
        "FTM": "4",
        "FTA": "4",
        "FT%": "100",
        "OREB": "2",
        "DREB": "11",
        "REB": "13",
        "AST": "2",
        "STL": "0",
        "BLK": "0",
        "TOV": "0",
        "PF": "4",
        "+/-": "18",
        "FP": "38.6"
    },
    {
        "Team": "UTA",
        "Match Up": "UTA vs. GSW",
        "Date": "04/11/2009",
        "Result": "L",
        "Minutes": "32",
        "Points": "25",
        "FGM": "10",
        "FGA": "18",
        "FG%": "55.6",
        "3PM": "0",
        "3PA": "0",
        "3P%": "-",
        "FTM": "5",
        "FTA": "5",
        "FT%": "100",
        "OREB": "4",
        "DREB": "8",
        "REB": "12",
        "AST": "1",
        "STL": "0",
        "BLK": "1",
        "TOV": "0",
        "PF": "3",
        "+/-": "-4",
        "FP": "43.9"
    },
    {
        "Team": "UTA",
        "Match Up": "UTA @ SAS",
        "Date": "04/10/2009",
        "Result": "L",
        "Minutes": "33",
        "Points": "15",
        "FGM": "4",
        "FGA": "12",
        "FG%": "33.3",
        "3PM": "0",
        "3PA": "0",
        "3P%": "-",
        "FTM": "7",
        "FTA": "10",
        "FT%": "70.0",
        "OREB": "1",
        "DREB": "7",
        "REB": "8",
        "AST": "1",
        "STL": "0",
        "BLK": "0",
        "TOV": "1",
        "PF": "4",
        "+/-": "-12",
        "FP": "25.1"
    },
    {
        "Team": "UTA",
        "Match Up": "UTA @ DAL",
        "Date": "04/08/2009",
        "Result": "L",
        "Minutes": "35",
        "Points": "10",
        "FGM": "5",
        "FGA": "11",
        "FG%": "45.5",
        "3PM": "0",
        "3PA": "0",
        "3P%": "-",
        "FTM": "0",
        "FTA": "2",
        "FT%": "0.0",
        "OREB": "4",
        "DREB": "7",
        "REB": "11",
        "AST": "3",
        "STL": "3",
        "BLK": "0",
        "TOV": "3",
        "PF": "3",
        "+/-": "-24",
        "FP": "33.7"
    },
    {
        "Team": "UTA",
        "Match Up": "UTA @ NOH",
        "Date": "04/05/2009",
        "Result": "W",
        "Minutes": "31",
        "Points": "10",
        "FGM": "5",
        "FGA": "10",
        "FG%": "50.0",
        "3PM": "0",
        "3PA": "0",
        "3P%": "-",
        "FTM": "0",
        "FTA": "0",
        "FT%": "-",
        "OREB": "3",
        "DREB": "7",
        "REB": "10",
        "AST": "2",
        "STL": "2",
        "BLK": "0",
        "TOV": "1",
        "PF": "2",
        "+/-": "3",
        "FP": "30.0"
    },
    {
        "Team": "UTA",
        "Match Up": "UTA vs. MIN",
        "Date": "04/03/2009",
        "Result": "L",
        "Minutes": "30",
        "Points": "6",
        "FGM": "1",
        "FGA": "9",
        "FG%": "11.1",
        "3PM": "0",
        "3PA": "0",
        "3P%": "-",
        "FTM": "4",
        "FTA": "4",
        "FT%": "100",
        "OREB": "1",
        "DREB": "4",
        "REB": "5",
        "AST": "2",
        "STL": "2",
        "BLK": "0",
        "TOV": "2",
        "PF": "3",
        "+/-": "-14",
        "FP": "19.0"
    },
    {
        "Team": "UTA",
        "Match Up": "UTA @ DEN",
        "Date": "04/02/2009",
        "Result": "L",
        "Minutes": "32",
        "Points": "15",
        "FGM": "7",
        "FGA": "23",
        "FG%": "30.4",
        "3PM": "0",
        "3PA": "0",
        "3P%": "-",
        "FTM": "1",
        "FTA": "2",
        "FT%": "50.0",
        "OREB": "8",
        "DREB": "3",
        "REB": "11",
        "AST": "4",
        "STL": "1",
        "BLK": "0",
        "TOV": "3",
        "PF": "5",
        "+/-": "4",
        "FP": "34.2"
    },
    {
        "Team": "UTA",
        "Match Up": "UTA @ POR",
        "Date": "03/31/2009",
        "Result": "L",
        "Minutes": "24",
        "Points": "20",
        "FGM": "10",
        "FGA": "12",
        "FG%": "83.3",
        "3PM": "0",
        "3PA": "0",
        "3P%": "-",
        "FTM": "0",
        "FTA": "0",
        "FT%": "-",
        "OREB": "2",
        "DREB": "1",
        "REB": "3",
        "AST": "1",
        "STL": "0",
        "BLK": "0",
        "TOV": "6",
        "PF": "3",
        "+/-": "-21",
        "FP": "19.1"
    },
    {
        "Team": "UTA",
        "Match Up": "UTA vs. NYK",
        "Date": "03/30/2009",
        "Result": "W",
        "Minutes": "42",
        "Points": "21",
        "FGM": "8",
        "FGA": "13",
        "FG%": "61.5",
        "3PM": "0",
        "3PA": "0",
        "3P%": "-",
        "FTM": "5",
        "FTA": "7",
        "FT%": "71.4",
        "OREB": "4",
        "DREB": "7",
        "REB": "11",
        "AST": "2",
        "STL": "4",
        "BLK": "0",
        "TOV": "3",
        "PF": "2",
        "+/-": "9",
        "FP": "46.2"
    },
    {
        "Team": "UTA",
        "Match Up": "UTA vs. PHX",
        "Date": "03/28/2009",
        "Result": "W",
        "Minutes": "28",
        "Points": "14",
        "FGM": "7",
        "FGA": "12",
        "FG%": "58.3",
        "3PM": "0",
        "3PA": "0",
        "3P%": "-",
        "FTM": "0",
        "FTA": "0",
        "FT%": "-",
        "OREB": "2",
        "DREB": "8",
        "REB": "10",
        "AST": "2",
        "STL": "1",
        "BLK": "0",
        "TOV": "3",
        "PF": "5",
        "+/-": "-8",
        "FP": "29.0"
    },
    {
        "Team": "UTA",
        "Match Up": "UTA @ PHX",
        "Date": "03/25/2009",
        "Result": "L",
        "Minutes": "38",
        "Points": "14",
        "FGM": "7",
        "FGA": "17",
        "FG%": "41.2",
        "3PM": "0",
        "3PA": "0",
        "3P%": "-",
        "FTM": "0",
        "FTA": "0",
        "FT%": "-",
        "OREB": "1",
        "DREB": "11",
        "REB": "12",
        "AST": "1",
        "STL": "1",
        "BLK": "0",
        "TOV": "1",
        "PF": "3",
        "+/-": "-3",
        "FP": "31.9"
    },
    {
        "Team": "UTA",
        "Match Up": "UTA vs. HOU",
        "Date": "03/24/2009",
        "Result": "W",
        "Minutes": "33",
        "Points": "13",
        "FGM": "6",
        "FGA": "15",
        "FG%": "40.0",
        "3PM": "0",
        "3PA": "0",
        "3P%": "-",
        "FTM": "1",
        "FTA": "2",
        "FT%": "50.0",
        "OREB": "0",
        "DREB": "8",
        "REB": "8",
        "AST": "1",
        "STL": "1",
        "BLK": "0",
        "TOV": "1",
        "PF": "5",
        "+/-": "9",
        "FP": "26.1"
    },
    {
        "Team": "UTA",
        "Match Up": "UTA @ OKC",
        "Date": "03/20/2009",
        "Result": "W",
        "Minutes": "42",
        "Points": "15",
        "FGM": "7",
        "FGA": "19",
        "FG%": "36.8",
        "3PM": "0",
        "3PA": "0",
        "3P%": "-",
        "FTM": "1",
        "FTA": "4",
        "FT%": "25.0",
        "OREB": "1",
        "DREB": "9",
        "REB": "10",
        "AST": "3",
        "STL": "0",
        "BLK": "0",
        "TOV": "3",
        "PF": "3",
        "+/-": "5",
        "FP": "28.5"
    },
    {
        "Team": "UTA",
        "Match Up": "UTA vs. WAS",
        "Date": "03/17/2009",
        "Result": "W",
        "Minutes": "34",
        "Points": "13",
        "FGM": "6",
        "FGA": "13",
        "FG%": "46.2",
        "3PM": "0",
        "3PA": "0",
        "3P%": "-",
        "FTM": "1",
        "FTA": "1",
        "FT%": "100",
        "OREB": "3",
        "DREB": "12",
        "REB": "15",
        "AST": "2",
        "STL": "1",
        "BLK": "0",
        "TOV": "1",
        "PF": "3",
        "+/-": "19",
        "FP": "36.0"
    },
    {
        "Team": "UTA",
        "Match Up": "UTA @ ORL",
        "Date": "03/15/2009",
        "Result": "L",
        "Minutes": "34",
        "Points": "23",
        "FGM": "11",
        "FGA": "20",
        "FG%": "55.0",
        "3PM": "0",
        "3PA": "0",
        "3P%": "-",
        "FTM": "1",
        "FTA": "2",
        "FT%": "50.0",
        "OREB": "2",
        "DREB": "11",
        "REB": "13",
        "AST": "2",
        "STL": "1",
        "BLK": "0",
        "TOV": "3",
        "PF": "4",
        "+/-": "-17",
        "FP": "41.6"
    },
    {
        "Team": "UTA",
        "Match Up": "UTA @ MIA",
        "Date": "03/14/2009",
        "Result": "L",
        "Minutes": "46",
        "Points": "20",
        "FGM": "8",
        "FGA": "18",
        "FG%": "44.4",
        "3PM": "0",
        "3PA": "0",
        "3P%": "-",
        "FTM": "4",
        "FTA": "5",
        "FT%": "80.0",
        "OREB": "4",
        "DREB": "9",
        "REB": "13",
        "AST": "4",
        "STL": "2",
        "BLK": "1",
        "TOV": "2",
        "PF": "4",
        "+/-": "-10",
        "FP": "48.6"
    },
    {
        "Team": "UTA",
        "Match Up": "UTA @ ATL",
        "Date": "03/11/2009",
        "Result": "L",
        "Minutes": "32",
        "Points": "13",
        "FGM": "6",
        "FGA": "11",
        "FG%": "54.5",
        "3PM": "0",
        "3PA": "0",
        "3P%": "-",
        "FTM": "1",
        "FTA": "2",
        "FT%": "50.0",
        "OREB": "3",
        "DREB": "5",
        "REB": "8",
        "AST": "2",
        "STL": "0",
        "BLK": "0",
        "TOV": "4",
        "PF": "5",
        "+/-": "6",
        "FP": "21.6"
    },
    {
        "Team": "UTA",
        "Match Up": "UTA @ IND",
        "Date": "03/10/2009",
        "Result": "W",
        "Minutes": "28",
        "Points": "11",
        "FGM": "4",
        "FGA": "13",
        "FG%": "30.8",
        "3PM": "0",
        "3PA": "0",
        "3P%": "-",
        "FTM": "3",
        "FTA": "4",
        "FT%": "75.0",
        "OREB": "2",
        "DREB": "5",
        "REB": "7",
        "AST": "0",
        "STL": "1",
        "BLK": "0",
        "TOV": "3",
        "PF": "4",
        "+/-": "1",
        "FP": "19.4"
    },
    {
        "Team": "UTA",
        "Match Up": "UTA vs. DEN",
        "Date": "03/06/2009",
        "Result": "W",
        "Minutes": "35",
        "Points": "9",
        "FGM": "4",
        "FGA": "12",
        "FG%": "33.3",
        "3PM": "0",
        "3PA": "0",
        "3P%": "-",
        "FTM": "1",
        "FTA": "2",
        "FT%": "50.0",
        "OREB": "5",
        "DREB": "11",
        "REB": "16",
        "AST": "1",
        "STL": "2",
        "BLK": "0",
        "TOV": "1",
        "PF": "4",
        "+/-": "5",
        "FP": "34.7"
    },
    {
        "Team": "UTA",
        "Match Up": "UTA vs. HOU",
        "Date": "03/04/2009",
        "Result": "W",
        "Minutes": "34",
        "Points": "20",
        "FGM": "8",
        "FGA": "17",
        "FG%": "47.1",
        "3PM": "0",
        "3PA": "0",
        "3P%": "-",
        "FTM": "4",
        "FTA": "4",
        "FT%": "100",
        "OREB": "5",
        "DREB": "12",
        "REB": "17",
        "AST": "3",
        "STL": "2",
        "BLK": "1",
        "TOV": "2",
        "PF": "5",
        "+/-": "15",
        "FP": "51.9"
    },
    {
        "Team": "UTA",
        "Match Up": "UTA @ GSW",
        "Date": "03/01/2009",
        "Result": "W",
        "Minutes": "20",
        "Points": "10",
        "FGM": "5",
        "FGA": "14",
        "FG%": "35.7",
        "3PM": "0",
        "3PA": "0",
        "3P%": "-",
        "FTM": "0",
        "FTA": "0",
        "FT%": "-",
        "OREB": "4",
        "DREB": "5",
        "REB": "9",
        "AST": "0",
        "STL": "2",
        "BLK": "0",
        "TOV": "3",
        "PF": "5",
        "+/-": "-1",
        "FP": "23.8"
    },
    {
        "Team": "UTA",
        "Match Up": "UTA vs. SAC",
        "Date": "02/28/2009",
        "Result": "W",
        "Minutes": "18",
        "Points": "6",
        "FGM": "3",
        "FGA": "5",
        "FG%": "60.0",
        "3PM": "0",
        "3PA": "0",
        "3P%": "-",
        "FTM": "0",
        "FTA": "2",
        "FT%": "0.0",
        "OREB": "1",
        "DREB": "4",
        "REB": "5",
        "AST": "3",
        "STL": "0",
        "BLK": "0",
        "TOV": "2",
        "PF": "1",
        "+/-": "2",
        "FP": "14.5"
    },
    {
        "Team": "UTA",
        "Match Up": "UTA @ MIN",
        "Date": "02/25/2009",
        "Result": "W",
        "Minutes": "22",
        "Points": "12",
        "FGM": "6",
        "FGA": "10",
        "FG%": "60.0",
        "3PM": "0",
        "3PA": "0",
        "3P%": "-",
        "FTM": "0",
        "FTA": "0",
        "FT%": "-",
        "OREB": "1",
        "DREB": "3",
        "REB": "4",
        "AST": "2",
        "STL": "0",
        "BLK": "0",
        "TOV": "3",
        "PF": "5",
        "+/-": "-8",
        "FP": "16.8"
    },
    {
        "Team": "UTA",
        "Match Up": "UTA vs. ATL",
        "Date": "02/23/2009",
        "Result": "W",
        "Minutes": "21",
        "Points": "2",
        "FGM": "1",
        "FGA": "5",
        "FG%": "20.0",
        "3PM": "0",
        "3PA": "0",
        "3P%": "-",
        "FTM": "0",
        "FTA": "2",
        "FT%": "0.0",
        "OREB": "2",
        "DREB": "3",
        "REB": "5",
        "AST": "2",
        "STL": "2",
        "BLK": "0",
        "TOV": "2",
        "PF": "2",
        "+/-": "1",
        "FP": "15.0"
    },
    {
        "Team": "UTA",
        "Match Up": "UTA vs. MIL",
        "Date": "11/19/2008",
        "Result": "W",
        "Minutes": "34",
        "Points": "20",
        "FGM": "9",
        "FGA": "17",
        "FG%": "52.9",
        "3PM": "0",
        "3PA": "0",
        "3P%": "-",
        "FTM": "2",
        "FTA": "6",
        "FT%": "33.3",
        "OREB": "2",
        "DREB": "9",
        "REB": "11",
        "AST": "3",
        "STL": "0",
        "BLK": "1",
        "TOV": "1",
        "PF": "4",
        "+/-": "4",
        "FP": "39.7"
    },
    {
        "Team": "UTA",
        "Match Up": "UTA vs. PHX",
        "Date": "11/17/2008",
        "Result": "W",
        "Minutes": "35",
        "Points": "21",
        "FGM": "7",
        "FGA": "15",
        "FG%": "46.7",
        "3PM": "0",
        "3PA": "0",
        "3P%": "-",
        "FTM": "7",
        "FTA": "11",
        "FT%": "63.6",
        "OREB": "7",
        "DREB": "8",
        "REB": "15",
        "AST": "4",
        "STL": "2",
        "BLK": "0",
        "TOV": "1",
        "PF": "4",
        "+/-": "1",
        "FP": "50.0"
    },
    {
        "Team": "UTA",
        "Match Up": "UTA @ CLE",
        "Date": "11/15/2008",
        "Result": "L",
        "Minutes": "37",
        "Points": "17",
        "FGM": "5",
        "FGA": "12",
        "FG%": "41.7",
        "3PM": "0",
        "3PA": "0",
        "3P%": "-",
        "FTM": "7",
        "FTA": "8",
        "FT%": "87.5",
        "OREB": "1",
        "DREB": "8",
        "REB": "9",
        "AST": "4",
        "STL": "0",
        "BLK": "0",
        "TOV": "2",
        "PF": "2",
        "+/-": "-20",
        "FP": "31.8"
    },
    {
        "Team": "UTA",
        "Match Up": "UTA @ CHA",
        "Date": "11/14/2008",
        "Result": "L",
        "Minutes": "33",
        "Points": "26",
        "FGM": "9",
        "FGA": "17",
        "FG%": "52.9",
        "3PM": "0",
        "3PA": "0",
        "3P%": "-",
        "FTM": "8",
        "FTA": "8",
        "FT%": "100",
        "OREB": "7",
        "DREB": "8",
        "REB": "15",
        "AST": "1",
        "STL": "1",
        "BLK": "0",
        "TOV": "2",
        "PF": "5",
        "+/-": "5",
        "FP": "46.5"
    },
    {
        "Team": "UTA",
        "Match Up": "UTA @ WAS",
        "Date": "11/12/2008",
        "Result": "L",
        "Minutes": "33",
        "Points": "20",
        "FGM": "9",
        "FGA": "17",
        "FG%": "52.9",
        "3PM": "0",
        "3PA": "0",
        "3P%": "-",
        "FTM": "2",
        "FTA": "4",
        "FT%": "50.0",
        "OREB": "3",
        "DREB": "4",
        "REB": "7",
        "AST": "2",
        "STL": "1",
        "BLK": "0",
        "TOV": "2",
        "PF": "6",
        "+/-": "-14",
        "FP": "32.4"
    },
    {
        "Team": "UTA",
        "Match Up": "UTA @ PHI",
        "Date": "11/11/2008",
        "Result": "W",
        "Minutes": "35",
        "Points": "19",
        "FGM": "9",
        "FGA": "15",
        "FG%": "60.0",
        "3PM": "0",
        "3PA": "0",
        "3P%": "-",
        "FTM": "1",
        "FTA": "3",
        "FT%": "33.3",
        "OREB": "4",
        "DREB": "12",
        "REB": "16",
        "AST": "2",
        "STL": "1",
        "BLK": "0",
        "TOV": "2",
        "PF": "3",
        "+/-": "0",
        "FP": "42.2"
    },
    {
        "Team": "UTA",
        "Match Up": "UTA @ NYK",
        "Date": "11/09/2008",
        "Result": "L",
        "Minutes": "32",
        "Points": "19",
        "FGM": "7",
        "FGA": "11",
        "FG%": "63.6",
        "3PM": "0",
        "3PA": "0",
        "3P%": "-",
        "FTM": "5",
        "FTA": "6",
        "FT%": "83.3",
        "OREB": "6",
        "DREB": "12",
        "REB": "18",
        "AST": "3",
        "STL": "3",
        "BLK": "0",
        "TOV": "2",
        "PF": "4",
        "+/-": "4",
        "FP": "52.1"
    },
    {
        "Team": "UTA",
        "Match Up": "UTA vs. OKC",
        "Date": "11/07/2008",
        "Result": "W",
        "Minutes": "38",
        "Points": "21",
        "FGM": "7",
        "FGA": "14",
        "FG%": "50.0",
        "3PM": "0",
        "3PA": "0",
        "3P%": "-",
        "FTM": "7",
        "FTA": "8",
        "FT%": "87.5",
        "OREB": "2",
        "DREB": "7",
        "REB": "9",
        "AST": "5",
        "STL": "1",
        "BLK": "1",
        "TOV": "6",
        "PF": "2",
        "+/-": "6",
        "FP": "39.3"
    },
    {
        "Team": "UTA",
        "Match Up": "UTA vs. POR",
        "Date": "11/05/2008",
        "Result": "W",
        "Minutes": "33",
        "Points": "20",
        "FGM": "8",
        "FGA": "13",
        "FG%": "61.5",
        "3PM": "0",
        "3PA": "0",
        "3P%": "-",
        "FTM": "4",
        "FTA": "4",
        "FT%": "100",
        "OREB": "2",
        "DREB": "6",
        "REB": "8",
        "AST": "3",
        "STL": "1",
        "BLK": "0",
        "TOV": "2",
        "PF": "2",
        "+/-": "3",
        "FP": "35.1"
    },
    {
        "Team": "UTA",
        "Match Up": "UTA @ LAC",
        "Date": "11/03/2008",
        "Result": "W",
        "Minutes": "29",
        "Points": "13",
        "FGM": "6",
        "FGA": "10",
        "FG%": "60.0",
        "3PM": "0",
        "3PA": "0",
        "3P%": "-",
        "FTM": "1",
        "FTA": "2",
        "FT%": "50.0",
        "OREB": "2",
        "DREB": "6",
        "REB": "8",
        "AST": "1",
        "STL": "0",
        "BLK": "0",
        "TOV": "2",
        "PF": "1",
        "+/-": "-3",
        "FP": "22.1"
    },
    {
        "Team": "UTA",
        "Match Up": "UTA vs. LAC",
        "Date": "11/01/2008",
        "Result": "W",
        "Minutes": "31",
        "Points": "25",
        "FGM": "12",
        "FGA": "18",
        "FG%": "66.7",
        "3PM": "0",
        "3PA": "0",
        "3P%": "-",
        "FTM": "1",
        "FTA": "2",
        "FT%": "50.0",
        "OREB": "4",
        "DREB": "6",
        "REB": "10",
        "AST": "3",
        "STL": "0",
        "BLK": "0",
        "TOV": "0",
        "PF": "2",
        "+/-": "9",
        "FP": "41.5"
    },
    {
        "Team": "UTA",
        "Match Up": "UTA vs. DEN",
        "Date": "10/29/2008",
        "Result": "W",
        "Minutes": "36",
        "Points": "25",
        "FGM": "11",
        "FGA": "18",
        "FG%": "61.1",
        "3PM": "0",
        "3PA": "0",
        "3P%": "-",
        "FTM": "3",
        "FTA": "4",
        "FT%": "75.0",
        "OREB": "3",
        "DREB": "11",
        "REB": "14",
        "AST": "1",
        "STL": "1",
        "BLK": "1",
        "TOV": "2",
        "PF": "5",
        "+/-": "3",
        "FP": "47.3"
    }
]