[
    {
        "Team": "MIL",
        "Match Up": "MIL vs. MIA",
        "Date": "04/26/2023",
        "Result": "L",
        "Minutes": "41",
        "Points": "33",
        "FGM": "10",
        "FGA": "24",
        "FG%": "41.7",
        "3PM": "4",
        "3PA": "10",
        "3P%": "40.0",
        "FTM": "9",
        "FTA": "9",
        "FT%": "100",
        "OREB": "1",
        "DREB": "5",
        "REB": "6",
        "AST": "6",
        "STL": "0",
        "BLK": "0",
        "TOV": "3",
        "PF": "5",
        "+/-": "-2",
        "FP": "46.2"
    },
    {
        "Team": "MIL",
        "Match Up": "MIL @ MIA",
        "Date": "04/24/2023",
        "Result": "L",
        "Minutes": "37",
        "Points": "14",
        "FGM": "4",
        "FGA": "12",
        "FG%": "33.3",
        "3PM": "2",
        "3PA": "5",
        "3P%": "40.0",
        "FTM": "4",
        "FTA": "4",
        "FT%": "100",
        "OREB": "2",
        "DREB": "4",
        "REB": "6",
        "AST": "8",
        "STL": "1",
        "BLK": "0",
        "TOV": "3",
        "PF": "6",
        "+/-": "5",
        "FP": "33.2"
    },
    {
        "Team": "MIL",
        "Match Up": "MIL @ MIA",
        "Date": "04/22/2023",
        "Result": "L",
        "Minutes": "34",
        "Points": "23",
        "FGM": "8",
        "FGA": "14",
        "FG%": "57.1",
        "3PM": "3",
        "3PA": "5",
        "3P%": "60.0",
        "FTM": "4",
        "FTA": "5",
        "FT%": "80.0",
        "OREB": "1",
        "DREB": "4",
        "REB": "5",
        "AST": "6",
        "STL": "2",
        "BLK": "0",
        "TOV": "5",
        "PF": "3",
        "+/-": "-10",
        "FP": "39.0"
    },
    {
        "Team": "MIL",
        "Match Up": "MIL vs. MIA",
        "Date": "04/19/2023",
        "Result": "W",
        "Minutes": "28",
        "Points": "16",
        "FGM": "6",
        "FGA": "16",
        "FG%": "37.5",
        "3PM": "2",
        "3PA": "5",
        "3P%": "40.0",
        "FTM": "2",
        "FTA": "2",
        "FT%": "100",
        "OREB": "1",
        "DREB": "5",
        "REB": "6",
        "AST": "7",
        "STL": "0",
        "BLK": "0",
        "TOV": "1",
        "PF": "0",
        "+/-": "19",
        "FP": "32.7"
    },
    {
        "Team": "MIL",
        "Match Up": "MIL vs. MIA",
        "Date": "04/16/2023",
        "Result": "L",
        "Minutes": "33",
        "Points": "33",
        "FGM": "12",
        "FGA": "20",
        "FG%": "60.0",
        "3PM": "2",
        "3PA": "7",
        "3P%": "28.6",
        "FTM": "7",
        "FTA": "10",
        "FT%": "70.0",
        "OREB": "2",
        "DREB": "7",
        "REB": "9",
        "AST": "4",
        "STL": "0",
        "BLK": "0",
        "TOV": "5",
        "PF": "1",
        "+/-": "1",
        "FP": "44.8"
    }
]