[
    {
        "Team": "WAS",
        "Match Up": "WAS @ GSW",
        "Date": "03/23/2015",
        "Result": "L",
        "Minutes": "4",
        "Points": "2",
        "FGM": "1",
        "FGA": "1",
        "FG%": "100",
        "3PM": "0",
        "3PA": "0",
        "3P%": "-",
        "FTM": "0",
        "FTA": "0",
        "FT%": "-",
        "OREB": "0",
        "DREB": "0",
        "REB": "0",
        "AST": "1",
        "STL": "0",
        "BLK": "0",
        "TOV": "1",
        "PF": "0",
        "+/-": "3",
        "FP": "2.5"
    },
    {
        "Team": "WAS",
        "Match Up": "WAS @ SAC",
        "Date": "03/22/2015",
        "Result": "L",
        "Minutes": "9",
        "Points": "0",
        "FGM": "0",
        "FGA": "2",
        "FG%": "0.0",
        "3PM": "0",
        "3PA": "0",
        "3P%": "-",
        "FTM": "0",
        "FTA": "0",
        "FT%": "-",
        "OREB": "1",
        "DREB": "0",
        "REB": "1",
        "AST": "0",
        "STL": "0",
        "BLK": "0",
        "TOV": "1",
        "PF": "0",
        "+/-": "-2",
        "FP": "0.2"
    },
    {
        "Team": "WAS",
        "Match Up": "WAS @ UTA",
        "Date": "03/18/2015",
        "Result": "W",
        "Minutes": "0",
        "Points": "0",
        "FGM": "0",
        "FGA": "0",
        "FG%": "-",
        "3PM": "0",
        "3PA": "0",
        "3P%": "-",
        "FTM": "0",
        "FTA": "0",
        "FT%": "-",
        "OREB": "0",
        "DREB": "0",
        "REB": "0",
        "AST": "0",
        "STL": "0",
        "BLK": "0",
        "TOV": "0",
        "PF": "0",
        "+/-": "0",
        "FP": "0.0"
    },
    {
        "Team": "WAS",
        "Match Up": "WAS vs. MEM",
        "Date": "03/12/2015",
        "Result": "W",
        "Minutes": "4",
        "Points": "4",
        "FGM": "1",
        "FGA": "1",
        "FG%": "100",
        "3PM": "0",
        "3PA": "0",
        "3P%": "-",
        "FTM": "2",
        "FTA": "2",
        "FT%": "100",
        "OREB": "0",
        "DREB": "0",
        "REB": "0",
        "AST": "0",
        "STL": "1",
        "BLK": "0",
        "TOV": "2",
        "PF": "2",
        "+/-": "1",
        "FP": "5.0"
    },
    {
        "Team": "UTA",
        "Match Up": "UTA @ MIN",
        "Date": "01/03/2015",
        "Result": "W",
        "Minutes": "1",
        "Points": "0",
        "FGM": "0",
        "FGA": "1",
        "FG%": "0.0",
        "3PM": "0",
        "3PA": "0",
        "3P%": "-",
        "FTM": "0",
        "FTA": "0",
        "FT%": "-",
        "OREB": "0",
        "DREB": "0",
        "REB": "0",
        "AST": "0",
        "STL": "0",
        "BLK": "0",
        "TOV": "0",
        "PF": "0",
        "+/-": "-2",
        "FP": "0.0"
    }
]