[
    {
        "Team": "MIN",
        "Match Up": "MIN @ HOU",
        "Date": "04/25/2018",
        "Result": "L",
        "Minutes": "37",
        "Points": "14",
        "FGM": "5",
        "FGA": "14",
        "FG%": "35.7",
        "3PM": "1",
        "3PA": "4",
        "3P%": "25.0",
        "FTM": "3",
        "FTA": "6",
        "FT%": "50.0",
        "OREB": "0",
        "DREB": "4",
        "REB": "4",
        "AST": "0",
        "STL": "0",
        "BLK": "0",
        "TOV": "2",
        "PF": "4",
        "+/-": "-16",
        "FP": "16.8"
    },
    {
        "Team": "MIN",
        "Match Up": "MIN vs. HOU",
        "Date": "04/23/2018",
        "Result": "L",
        "Minutes": "29",
        "Points": "14",
        "FGM": "5",
        "FGA": "14",
        "FG%": "35.7",
        "3PM": "1",
        "3PA": "5",
        "3P%": "20.0",
        "FTM": "3",
        "FTA": "4",
        "FT%": "75.0",
        "OREB": "0",
        "DREB": "3",
        "REB": "3",
        "AST": "1",
        "STL": "0",
        "BLK": "0",
        "TOV": "1",
        "PF": "2",
        "+/-": "-30",
        "FP": "18.1"
    },
    {
        "Team": "MIN",
        "Match Up": "MIN vs. HOU",
        "Date": "04/21/2018",
        "Result": "W",
        "Minutes": "35",
        "Points": "20",
        "FGM": "7",
        "FGA": "11",
        "FG%": "63.6",
        "3PM": "4",
        "3PA": "6",
        "3P%": "66.7",
        "FTM": "2",
        "FTA": "4",
        "FT%": "50.0",
        "OREB": "2",
        "DREB": "3",
        "REB": "5",
        "AST": "5",
        "STL": "1",
        "BLK": "1",
        "TOV": "1",
        "PF": "1",
        "+/-": "5",
        "FP": "38.5"
    },
    {
        "Team": "MIN",
        "Match Up": "MIN @ HOU",
        "Date": "04/18/2018",
        "Result": "L",
        "Minutes": "31",
        "Points": "13",
        "FGM": "6",
        "FGA": "14",
        "FG%": "42.9",
        "3PM": "0",
        "3PA": "3",
        "3P%": "0.0",
        "FTM": "1",
        "FTA": "2",
        "FT%": "50.0",
        "OREB": "1",
        "DREB": "7",
        "REB": "8",
        "AST": "3",
        "STL": "1",
        "BLK": "1",
        "TOV": "3",
        "PF": "3",
        "+/-": "-12",
        "FP": "30.1"
    },
    {
        "Team": "MIN",
        "Match Up": "MIN @ HOU",
        "Date": "04/15/2018",
        "Result": "L",
        "Minutes": "32",
        "Points": "18",
        "FGM": "7",
        "FGA": "15",
        "FG%": "46.7",
        "3PM": "1",
        "3PA": "3",
        "3P%": "33.3",
        "FTM": "3",
        "FTA": "4",
        "FT%": "75.0",
        "OREB": "2",
        "DREB": "4",
        "REB": "6",
        "AST": "1",
        "STL": "0",
        "BLK": "0",
        "TOV": "2",
        "PF": "4",
        "+/-": "-3",
        "FP": "24.7"
    }
]