[
    {
        "Team": "NOP",
        "Match Up": "NOP vs. GSW",
        "Date": "04/25/2015",
        "Result": "L",
        "Minutes": "14",
        "Points": "3",
        "FGM": "1",
        "FGA": "4",
        "FG%": "25.0",
        "3PM": "0",
        "3PA": "0",
        "3P%": "-",
        "FTM": "1",
        "FTA": "1",
        "FT%": "100",
        "OREB": "1",
        "DREB": "0",
        "REB": "1",
        "AST": "2",
        "STL": "1",
        "BLK": "0",
        "TOV": "0",
        "PF": "1",
        "+/-": "-5",
        "FP": "10.2"
    },
    {
        "Team": "NOP",
        "Match Up": "NOP vs. GSW",
        "Date": "04/23/2015",
        "Result": "L",
        "Minutes": "20",
        "Points": "1",
        "FGM": "0",
        "FGA": "2",
        "FG%": "0.0",
        "3PM": "0",
        "3PA": "0",
        "3P%": "-",
        "FTM": "1",
        "FTA": "2",
        "FT%": "50.0",
        "OREB": "3",
        "DREB": "3",
        "REB": "6",
        "AST": "1",
        "STL": "1",
        "BLK": "0",
        "TOV": "1",
        "PF": "1",
        "+/-": "-8",
        "FP": "11.7"
    },
    {
        "Team": "NOP",
        "Match Up": "NOP @ GSW",
        "Date": "04/20/2015",
        "Result": "L",
        "Minutes": "24",
        "Points": "2",
        "FGM": "1",
        "FGA": "3",
        "FG%": "33.3",
        "3PM": "0",
        "3PA": "0",
        "3P%": "-",
        "FTM": "0",
        "FTA": "0",
        "FT%": "-",
        "OREB": "6",
        "DREB": "7",
        "REB": "13",
        "AST": "2",
        "STL": "2",
        "BLK": "0",
        "TOV": "3",
        "PF": "5",
        "+/-": "-5",
        "FP": "23.6"
    },
    {
        "Team": "NOP",
        "Match Up": "NOP @ GSW",
        "Date": "04/18/2015",
        "Result": "L",
        "Minutes": "22",
        "Points": "2",
        "FGM": "0",
        "FGA": "1",
        "FG%": "0.0",
        "3PM": "0",
        "3PA": "0",
        "3P%": "-",
        "FTM": "2",
        "FTA": "4",
        "FT%": "50.0",
        "OREB": "2",
        "DREB": "7",
        "REB": "9",
        "AST": "1",
        "STL": "1",
        "BLK": "0",
        "TOV": "1",
        "PF": "3",
        "+/-": "-18",
        "FP": "16.3"
    }
]